Database_comparator/Fasta_maker.py
Database_comparator/__init__.py
Database_comparator/config_class.py
Database_comparator/db_aligner.py
Database_comparator/db_blast.py
Database_comparator/db_compare.py
Database_comparator/db_exact_match.py
Database_comparator/db_fast_hamming.py
Database_comparator/db_hamming.py
Database_comparator/db_testing.py
Database_comparator/run_independent_test.py
database_comparator-1.1.6.dist-info/licenses/LICENSE
database_comparator-1.1.6.dist-info/METADATA
database_comparator-1.1.6.dist-info/WHEEL
database_comparator-1.1.6.dist-info/top_level.txt
database_comparator-1.1.6.dist-info/RECORD
