Metadata-Version: 2.4
Name: database_comparator
Version: 1.1.6
Summary: Bioinformatics tool for compering large sequence files
Author: preislet (Tomáš Preisler)
Author-email: <tomas.preisler1@gmail.com>
Classifier: Development Status :: 4 - Beta
Classifier: Intended Audience :: Science/Research
Classifier: Programming Language :: Python :: 3
Classifier: Operating System :: Unix
Classifier: Operating System :: MacOS :: MacOS X
Classifier: Operating System :: Microsoft :: Windows
License-File: LICENSE
Requires-Dist: setuptools
Requires-Dist: pandas
Requires-Dist: bio
Requires-Dist: numpy
Requires-Dist: pyreadr
Requires-Dist: tabulate
Requires-Dist: openpyxl
Requires-Dist: joblib
Dynamic: author
Dynamic: author-email
Dynamic: classifier
Dynamic: description
Dynamic: description-content-type
Dynamic: license-file
Dynamic: requires-dist
Dynamic: summary
